{"assets/images/market_logo.png":["assets/images/market_logo.png"],"assets/images/products/abacate.png":["assets/images/products/abacate.png"],"assets/images/products/abobora.png":["assets/images/products/abobora.png"],"assets/images/products/alho.png":["assets/images/products/alho.png"],"assets/images/products/batata.png":["assets/images/products/batata.png"],"assets/images/products/cenoura.png":["assets/images/products/cenoura.png"],"assets/images/products/espinafre.png":["assets/images/products/espinafre.png"],"assets/images/products/kiwi.png":["assets/images/products/kiwi.png"],"assets/images/products/melancia.png":["assets/images/products/melancia.png"],"assets/images/products/mirtilo.png":["assets/images/products/mirtilo.png"],"assets/images/products/morango.png":["assets/images/products/morango.png"],"assets/images/products/pimenta.png":["assets/images/products/pimenta.png"],"packages/cupertino_icons/assets/CupertinoIcons.ttf":["packages/cupertino_icons/assets/CupertinoIcons.ttf"]}